MakanaLibrary/__init__.py
MakanaLibrary/authService.py
MakanaLibrary/makana.py
MakanaLibrary/test.py
MakanaLibrary-0.1.0.dist-info/LICENSE.txt
MakanaLibrary-0.1.0.dist-info/METADATA
MakanaLibrary-0.1.0.dist-info/WHEEL
MakanaLibrary-0.1.0.dist-info/top_level.txt
MakanaLibrary-0.1.0.dist-info/RECORD
